Metadata-Version: 2.1
Name: ragstack-ai-langflow-base
Version: 1.0.18.post1
Summary: RAGStack Langflow base
Home-page: https://github.com/datastax/ragstack-ai-langflow
License: BUSL-1.1
Keywords: nlp,langchain,openai,gpt,gui
Author: DataStax
Maintainer: Carlos Coelho
Maintainer-email: carlos@langflow.org
Requires-Python: >=3.10,<3.13
Classifier: License :: Other/Proprietary License
Classifier: Programming Language :: Python :: 3
Classifier: Programming Language :: Python :: 3.10
Classifier: Programming Language :: Python :: 3.11
Classifier: Programming Language :: Python :: 3.12
Provides-Extra: all
Provides-Extra: deploy
Provides-Extra: local
Requires-Dist: aiofiles (>=24.1.0,<25.0.0)
Requires-Dist: alembic (>=1.13.0,<2.0.0)
Requires-Dist: asyncer (>=0.0.5,<0.0.6)
Requires-Dist: bcrypt (==4.0.1)
Requires-Dist: cachetools (>=5.3.1,<6.0.0)
Requires-Dist: chardet (>=5.2.0,<6.0.0)
Requires-Dist: clickhouse-connect (==0.7.19)
Requires-Dist: crewai (>=0.36.0,<0.37.0)
Requires-Dist: cryptography (>=42.0.5,<44.0.0)
Requires-Dist: diskcache (>=5.6.3,<6.0.0)
Requires-Dist: docstring-parser (>=0.16,<0.17)
Requires-Dist: duckdb (>=1.0.0,<2.0.0)
Requires-Dist: emoji (>=2.12.0,<3.0.0)
Requires-Dist: fastapi (>=0.111.0,<0.112.0)
Requires-Dist: filelock (>=3.15.4,<4.0.0)
Requires-Dist: firecrawl-py (>=0.0.16,<0.0.17)
Requires-Dist: grandalf (>=0.8.0,<0.9.0)
Requires-Dist: gunicorn (>=22.0.0,<23.0.0)
Requires-Dist: httpx
Requires-Dist: jq (>=1.7.0,<2.0.0) ; sys_platform != "win32"
Requires-Dist: langchain (>=0.2.0,<0.3.0)
Requires-Dist: langchain-core (>=0.2.32,<0.3.0)
Requires-Dist: langchain-experimental (>=0.0.61,<0.0.62)
Requires-Dist: langchainhub (>=0.1.15,<0.2.0)
Requires-Dist: loguru (>=0.7.1,<0.8.0)
Requires-Dist: multiprocess (>=0.70.14,<0.71.0)
Requires-Dist: nanoid (>=2.0.0,<3.0.0)
Requires-Dist: nest-asyncio (>=1.6.0,<2.0.0)
Requires-Dist: opentelemetry-api (>=1.25.0,<2.0.0)
Requires-Dist: opentelemetry-exporter-prometheus (>=0.46b0,<0.47)
Requires-Dist: opentelemetry-instrumentation-fastapi (>=0.46b0,<0.47)
Requires-Dist: opentelemetry-sdk (>=1.25.0,<2.0.0)
Requires-Dist: orjson (==3.10.0)
Requires-Dist: pandas (==2.2.2)
Requires-Dist: passlib (>=1.7.4,<2.0.0)
Requires-Dist: pillow (>=10.2.0,<11.0.0)
Requires-Dist: platformdirs (>=4.2.0,<5.0.0)
Requires-Dist: prometheus-client (>=0.20.0,<0.21.0)
Requires-Dist: pydantic (>=2.7.0,<3.0.0)
Requires-Dist: pydantic-settings (>=2.2.0,<3.0.0)
Requires-Dist: pypdf (>=4.2.0,<5.0.0)
Requires-Dist: pyperclip (>=1.8.2,<2.0.0)
Requires-Dist: python-docx (>=1.1.0,<2.0.0)
Requires-Dist: python-jose (>=3.3.0,<4.0.0)
Requires-Dist: python-multipart (>=0.0.7,<0.0.8)
Requires-Dist: rich (>=13.7.0,<14.0.0)
Requires-Dist: sentry-sdk[fastapi,loguru] (>=2.5.1,<3.0.0)
Requires-Dist: setuptools (>=70)
Requires-Dist: spider-client (>=0.0.27,<0.0.28)
Requires-Dist: sqlmodel (>=0.0.18,<0.0.19)
Requires-Dist: typer (>=0.12.0,<0.13.0)
Requires-Dist: uncurl (>=0.0.11,<0.0.12)
Requires-Dist: uvicorn (>=0.30.0,<0.31.0)
Requires-Dist: websockets
Project-URL: Documentation, https://docs.datastax.com/en/ragstack
Project-URL: Repository, https://github.com/datastax/ragstack-ai-langflow
